xedocs/__init__.py
xedocs/_settings.py
xedocs/_straxen_plugin.py
xedocs/cli.py
xedocs/clock.py
xedocs/data_locations/__init__.py
xedocs/data_locations/api.py
xedocs/data_locations/corrections_repo.py
xedocs/data_locations/data_folder.py
xedocs/data_locations/github.py
xedocs/data_locations/mongodb.py
xedocs/databases.py
xedocs/dispatchers.py
xedocs/entrypoints.py
xedocs/json_records.py
xedocs/regex_dispatcher.py
xedocs/schemas/__init__.py
xedocs/schemas/analysis/__init__.py
xedocs/schemas/analysis/base_analysis.py
xedocs/schemas/analysis/processing_requests.py
xedocs/schemas/base_schemas.py
xedocs/schemas/calibrations/__init__.py
xedocs/schemas/calibrations/base_calibrations.py
xedocs/schemas/calibrations/diffused_calibration.py
xedocs/schemas/calibrations/ibelt_calibrations.py
xedocs/schemas/calibrations/sources.py
xedocs/schemas/calibrations/utube_calibrations.py
xedocs/schemas/constants.py
xedocs/schemas/context_config.py
xedocs/schemas/context_lineage.py
xedocs/schemas/corrections/__init__.py
xedocs/schemas/corrections/base_corrections.py
xedocs/schemas/corrections/base_references.py
xedocs/schemas/corrections/implementations/__init__.py
xedocs/schemas/corrections/implementations/avg_se_gain.py
xedocs/schemas/corrections/implementations/baseline_samples_nv.py
xedocs/schemas/corrections/implementations/bayes_model.py
xedocs/schemas/corrections/implementations/cs2_aft_corrections.py
xedocs/schemas/corrections/implementations/electron_diffusion_cte.py
xedocs/schemas/corrections/implementations/electron_drift.py
xedocs/schemas/corrections/implementations/electron_lifetime.py
xedocs/schemas/corrections/implementations/extraction_efficiency.py
xedocs/schemas/corrections/implementations/field_distortion.py
xedocs/schemas/corrections/implementations/field_simulation.py
xedocs/schemas/corrections/implementations/global_versions.py
xedocs/schemas/corrections/implementations/hit_thresholds.py
xedocs/schemas/corrections/implementations/hotspot_veto_cut.py
xedocs-0.2.43.dist-info/METADATA
xedocs-0.2.43.dist-info/WHEEL
xedocs-0.2.43.dist-info/entry_points.txt
xedocs-0.2.43.dist-info/licenses/AUTHORS.rst
xedocs-0.2.43.dist-info/RECORD
