Metadata-Version: 2.4
Name: xedocs
Version: 0.2.43
Summary: Top-level package for xedocs.
License-File: AUTHORS.rst
Author: Yossi Mosbacher
Author-email: joe.mosbacher@gmail.com
Requires-Python: >=3.9,<3.13
Classifier: Development Status :: 2 - Pre-Alpha
Classifier: Intended Audience :: Developers
Classifier: Natural Language :: English
Classifier: Programming Language :: Python :: 3
Classifier: Programming Language :: Python :: 3.9
Classifier: Programming Language :: Python :: 3.10
Classifier: Programming Language :: Python :: 3.11
Classifier: Programming Language :: Python :: 3.12
Provides-Extra: all
Provides-Extra: db
Requires-Dist: appdirs (>=1.4.4,<2.0.0)
Requires-Dist: click
Requires-Dist: parse (>=1.20.2,<2.0.0)
Requires-Dist: pymongo ; extra == "db"
Requires-Dist: pyyaml (>=6.0,<7.0)
Requires-Dist: rframe (>=0.2.23,<0.3.0)
Requires-Dist: rich
Requires-Dist: tinydb (>=4.8.2,<5.0.0)
Requires-Dist: tqdm (>=4.67.1,<5.0.0)
Requires-Dist: xeauth (>=0.2.3,<0.3.0)
Project-URL: Homepage, https://github.com/XENONnT/xedocs
